log_distance_measures/__init__.py
log_distance_measures/absolute_event_distribution.py
log_distance_measures/case_arrival_distribution.py
log_distance_measures/circadian_event_distribution.py
log_distance_measures/circadian_workforce_distribution.py
log_distance_measures/config.py
log_distance_measures/control_flow_log_distance.py
log_distance_measures/cycle_time_distribution.py
log_distance_measures/earth_movers_distance.py
log_distance_measures/n_gram_distribution.py
log_distance_measures/relative_event_distribution.py
log_distance_measures/remaining_time_distribution.py
log_distance_measures/work_in_progress.py
log_distance_measures-2.1.0.dist-info/LICENSE
log_distance_measures-2.1.0.dist-info/METADATA
log_distance_measures-2.1.0.dist-info/WHEEL
log_distance_measures-2.1.0.dist-info/RECORD
