Metadata-Version: 2.3
Name: log-distance-measures
Version: 2.1.0
Summary: Python package with the implementation of different distance measures between two event logs, from the control-flow, temporal, and queuing perspectives.
Author: David Chapela de la Campa
Author-email: david.chapela.delacampa@gmail.com
Requires-Python: >=3.9,<3.12
Classifier: Programming Language :: Python :: 3
Classifier: Programming Language :: Python :: 3.9
Classifier: Programming Language :: Python :: 3.10
Classifier: Programming Language :: Python :: 3.11
Requires-Dist: jellyfish (>=0.11.2,<0.12.0)
Requires-Dist: pandas (>=2.0.0,<3.0.0)
Requires-Dist: pulp (>=2.7.0,<3.0.0)
Requires-Dist: scipy (>=1.10.1,<2.0.0)
